pytest_regex_dependency.py
pytest_regex_dependency-0.1.1.dist-info/LICENSE
pytest_regex_dependency-0.1.1.dist-info/METADATA
pytest_regex_dependency-0.1.1.dist-info/WHEEL
pytest_regex_dependency-0.1.1.dist-info/entry_points.txt
pytest_regex_dependency-0.1.1.dist-info/top_level.txt
pytest_regex_dependency-0.1.1.dist-info/RECORD
