Metadata-Version: 2.1
Name: pytest-regex-dependency
Version: 0.1.1
Summary: Management of Pytest dependencies via regex patterns
Home-page: https://github.com/marshall7m/pytest-regex-dependency
Author: Marshall Mamiya
Project-URL: Bug Tracker, https://github.com/marshall7m/pytest-regex-dependency
Classifier: Programming Language :: Python :: 3
Classifier: License :: OSI Approved :: Apache Software License
Classifier: Operating System :: OS Independent
Classifier: Framework :: Pytest
License-File: LICENSE
Requires-Dist: pytest
